{
  "app_name": "QuitMate",
  "welcome": "Добро пожаловать в QuitMate!",
  "welcome_subtitle": "Ваш путь к жизни без курения начинается здесь",
  "get_started": "Начать",
  "skip": "Пропустить",
  
  "auth": {
    "sign_in_google": "Войти через Google",
    "sign_in_email": "Войти по Email",
    "sign_up": "Регистрация",
    "email": "Email",
    "password": "Пароль",
    "confirm_password": "Подтвердите пароль",
    "display_name": "Имя пользователя",
    "forgot_password": "Забыли пароль?",
    "reset_password": "Сброс пароля",
    "send_reset_link": "Отправить ссылку для сброса",
    "already_have_account": "Уже есть аккаунт?",
    "dont_have_account": "Нет аккаунта?",
    "sign_in": "Войти",
    "sign_out": "Выйти"
  },
  
  "home": {
    "welcome": "Добро пожаловать",
    "days_smoke_free": "Дней без сигарет",
    "cigarettes_avoided": "Не выкурено сигарет",
    "money_saved": "Сэкономлено денег",
    "health_stage": "Этап восстановления",
    "craving_button": "🆘 Тяга",
    "set_quit_date": "Установить дату отказа",
    "no_quit_date": "Дата отказа не установлена"
  },
  
  "progress": {
    "title": "Прогресс",
    "calendar": "Календарь",
    "achievements": "Достижения",
    "stats": "Статистика",
    "chart_title": "График прогресса",
    "days": "Дни",
    "cigarettes": "Сигареты",
    "money": "Деньги"
  },
  
  "achievements": {
    "day_1": "Первый день",
    "day_3": "Три дня",
    "week_1": "Неделя",
    "week_2": "Две недели",
    "month_1": "Месяц",
    "month_3": "Три месяца",
    "month_6": "Полгода",
    "year_1": "Год",
    "locked": "Заблокировано",
    "unlocked": "Разблокировано"
  },
  
  "motivation": {
    "title": "Мотивация",
    "daily_quote": "Цитата дня",
    "my_reasons": "Мои причины",
    "add_reason": "Добавить причину",
    "reason_placeholder": "Почему вы бросаете курить?",
    "add_reason_button": "Добавить",
    "remove_reason": "Удалить"
  },
  
  "settings": {
    "title": "Настройки",
    "language": "Язык",
    "theme": "Тема",
    "notifications": "Уведомления",
    "smoking_settings": "Настройки курения",
    "cigarettes_per_day": "Сигарет в день",
    "pack_price": "Цена пачки",
    "currency": "Валюта",
    "quit_date": "Дата отказа",
    "select_date": "Выбрать дату",
    "save": "Сохранить",
    "cancel": "Отмена",
    "reset": "Сброс",
    "about": "О приложении",
    "version": "Версия",
    "privacy_policy": "Политика конфиденциальности",
    "terms_of_service": "Условия использования"
  },
  
  "themes": {
    "light": "Светлая",
    "dark": "Тёмная",
    "system": "Системная"
  },
  
  "languages": {
    "en": "English",
    "ru": "Русский"
  },
  
  "currencies": {
    "USD": "USD ($)",
    "RUB": "RUB (₽)",
    "EUR": "EUR (€)"
  },
  
  "health_stages": {
    "start": "Начало пути",
    "first_days": "Первые дни",
    "week_1": "Неделя без курения",
    "week_2": "Две недели",
    "month_1": "Месяц без курения",
    "month_3": "Три месяца",
    "month_6": "Полгода",
    "year_1": "Год без курения",
    "more_than_year": "Более года"
  },
  
  "craving": {
    "title": "Поддержка при тяге",
    "breathing_exercise": "Дыхательная практика",
    "tips": "Советы для преодоления тяги",
    "tip_1": "Сделайте глубокие вдохи",
    "tip_2": "Выпейте воды",
    "tip_3": "Прогуляйтесь",
    "tip_4": "Позвоните другу",
    "tip_5": "Вспомните свои причины",
    "start_breathing": "Начать дыхательную практику",
    "stop_breathing": "Остановить",
    "inhale": "Вдох",
    "exhale": "Выдох"
  },
  
  "errors": {
    "general": "Что-то пошло не так",
    "network": "Ошибка сети",
    "auth_failed": "Ошибка аутентификации",
    "invalid_email": "Неверный email",
    "weak_password": "Слишком слабый пароль",
    "email_already_in_use": "Email уже используется",
    "user_not_found": "Пользователь не найден",
    "wrong_password": "Неверный пароль"
  },
  
  "success": {
    "settings_saved": "Настройки сохранены",
    "reason_added": "Причина добавлена",
    "reason_removed": "Причина удалена",
    "quit_date_set": "Дата отказа установлена",
    "password_reset_sent": "Email для сброса пароля отправлен"
  },
  
  "confirmations": {
    "delete_reason": "Удалить причину",
    "delete_reason_message": "Вы уверены, что хотите удалить эту причину?",
    "sign_out": "Выйти",
    "sign_out_message": "Вы уверены, что хотите выйти?",
    "yes": "Да",
    "no": "Нет"
  }
} 